tgkit.py
tgkit-0.1.0a0.dist-info/LICENSE.md
tgkit-0.1.0a0.dist-info/METADATA
tgkit-0.1.0a0.dist-info/WHEEL
tgkit-0.1.0a0.dist-info/top_level.txt
tgkit-0.1.0a0.dist-info/RECORD
