Metadata-Version: 2.1
Name: tgkit
Version: 0.1.0a0
Summary: Python package to convert Temporal Graphs to Discrete (snapshot-based) or Continuous (event-based) format.
Home-page: https://github.com/nelsonaloysio/tgkit
Author: Nelson Aloysio Reis de Almeida Passos
License: MIT
Project-URL: Source, https://github.com/nelsonaloysio/tgkit
Project-URL: Tracker, https://github.com/nelsonaloysio/tgkit/issues
Keywords: Network,Graph,Dynamic Network,Temporal Graph
Classifier: Development Status :: 3 - Alpha
Classifier: Intended Audience :: Developers
Classifier: Intended Audience :: Information Technology
Classifier: License :: OSI Approved :: MIT License
Classifier: Programming Language :: Python :: 3
Classifier: Topic :: Scientific/Engineering :: Information Analysis
Classifier: Topic :: Software Development :: Libraries :: Python Modules
Requires-Python: >=3.7
License-File: LICENSE.md
Requires-Dist: networkx >=2.1
Requires-Dist: torch-geometric >=2.3.0
Requires-Dist: torch-geometric-temporal >=0.54
